pactus_grpc/__init__.py
pactus_grpc/__init__.pyi
pactus_grpc/blockchain_pb2.py
pactus_grpc/blockchain_pb2.pyi
pactus_grpc/blockchain_pb2_grpc.py
pactus_grpc/network_pb2.py
pactus_grpc/network_pb2.pyi
pactus_grpc/network_pb2_grpc.py
pactus_grpc/transaction_pb2.py
pactus_grpc/transaction_pb2.pyi
pactus_grpc/transaction_pb2_grpc.py
pactus_grpc/utils_pb2.py
pactus_grpc/utils_pb2.pyi
pactus_grpc/utils_pb2_grpc.py
pactus_grpc/wallet_pb2.py
pactus_grpc/wallet_pb2.pyi
pactus_grpc/wallet_pb2_grpc.py
pactus_grpc-1.11.1.dist-info/licenses/LICENSE
pactus_grpc-1.11.1.dist-info/METADATA
pactus_grpc-1.11.1.dist-info/WHEEL
pactus_grpc-1.11.1.dist-info/top_level.txt
pactus_grpc-1.11.1.dist-info/RECORD
