Metadata-Version: 2.4
Name: pactus-grpc
Version: 1.11.1
Summary: Python client for interacting with the Pactus blockchain via gRPC
Home-page: https://pactus.org
Author: Pactus Development Team
Author-email: info@pactus.org
License: MIT
Keywords: pactus,blockchain,grpc
Classifier: Development Status :: 5 - Production/Stable
Classifier: Intended Audience :: Developers
Classifier: Topic :: Software Development :: Build Tools
Classifier: Operating System :: OS Independent
Requires-Python: >=3.6
License-File: LICENSE
Requires-Dist: grpcio
Requires-Dist: protobuf
Dynamic: author
Dynamic: author-email
Dynamic: classifier
Dynamic: description
Dynamic: description-content-type
Dynamic: home-page
Dynamic: keywords
Dynamic: license
Dynamic: license-file
Dynamic: requires-dist
Dynamic: requires-python
Dynamic: summary
